odoo/addons/l10n_br_account_payment_order/README.rst
odoo/addons/l10n_br_account_payment_order/__init__.py
odoo/addons/l10n_br_account_payment_order/__manifest__.py
odoo/addons/l10n_br_account_payment_order/constants.py
odoo/addons/l10n_br_account_payment_order/data/boleto_data.xml
odoo/addons/l10n_br_account_payment_order/data/cnab_data.xml
odoo/addons/l10n_br_account_payment_order/data/l10n_br_payment_export_type.xml
odoo/addons/l10n_br_account_payment_order/data/cnab_codes/banco_ailos_240_boleto_discount_code.xml
odoo/addons/l10n_br_account_payment_order/data/cnab_codes/banco_ailos_cnab_240.xml
odoo/addons/l10n_br_account_payment_order/data/cnab_codes/banco_bradesco_240_boleto_discount_code.xml
odoo/addons/l10n_br_account_payment_order/data/cnab_codes/banco_bradesco_boleto_wallet_code.xml
odoo/addons/l10n_br_account_payment_order/data/cnab_codes/banco_bradesco_cnab_240_400.xml
odoo/addons/l10n_br_account_payment_order/data/cnab_codes/banco_cef_240_boleto_discount_code.xml
odoo/addons/l10n_br_account_payment_order/data/cnab_codes/banco_cef_cnab_240.xml
odoo/addons/l10n_br_account_payment_order/data/cnab_codes/banco_do_brasil_cnab_240.xml
odoo/addons/l10n_br_account_payment_order/data/cnab_codes/banco_do_brasil_cnab_400.xml
odoo/addons/l10n_br_account_payment_order/data/cnab_codes/banco_itau_cnab_240_400.xml
odoo/addons/l10n_br_account_payment_order/data/cnab_codes/banco_santander_240_boleto_discount_code.xml
odoo/addons/l10n_br_account_payment_order/data/cnab_codes/banco_santander_240_boleto_write_off_devolution.xml
odoo/addons/l10n_br_account_payment_order/data/cnab_codes/banco_santander_boleto_wallet_code.xml
odoo/addons/l10n_br_account_payment_order/data/cnab_codes/banco_santander_cnab_240_400.xml
odoo/addons/l10n_br_account_payment_order/data/cnab_codes/banco_sicred_cnab_240.xml
odoo/addons/l10n_br_account_payment_order/data/cnab_codes/banco_sicredi_240_boleto_discount_code.xml
odoo14_addon_l10n_br_account_payment_order-14.0.9.4.2.dist-info/METADATA
odoo14_addon_l10n_br_account_payment_order-14.0.9.4.2.dist-info/WHEEL
odoo14_addon_l10n_br_account_payment_order-14.0.9.4.2.dist-info/top_level.txt
odoo14_addon_l10n_br_account_payment_order-14.0.9.4.2.dist-info/RECORD
