Metadata-Version: 2.1
Name: odoo14-addon-l10n_br_account_payment_order
Version: 14.0.9.4.2
Summary: Brazilian Payment Order
Home-page: https://github.com/OCA/l10n-brazil
Author: KMEE, Akretion, Odoo Community Association (OCA)
Author-email: support@odoo-community.org
License: AGPL-3
Classifier: Programming Language :: Python
Classifier: Framework :: Odoo
Classifier: Framework :: Odoo :: 14.0
Classifier: License :: OSI Approved :: GNU Affero General Public License v3
Requires-Python: >=3.6
Requires-Dist: erpbrasil.base
Requires-Dist: odoo14-addon-account-due-list-payment-mode
Requires-Dist: odoo14-addon-account-payment-order
Requires-Dist: odoo14-addon-l10n-br-account-due-list
Requires-Dist: odoo14-addon-l10n-br-base
Requires-Dist: odoo<14.1dev,>=14.0a
